README.rst
setup.py
bin/wfwt-update-history
bin/workflowtool
test/test_report_action.py
test/test_workflowwebtools.py
workflowmonit/__init__.py
workflowmonit/alertingDefs.py
workflowmonit/dumpWfStatusDb.py
workflowmonit/sendToMonit.py
workflowmonit/workflowCollector.py
workflowmonit/workflowMonitScheduler.py
workflowwebtools/__init__.py
workflowwebtools/actionshistorylink.py
workflowwebtools/classifyerrors.py
workflowwebtools/clusterworkflows.py
workflowwebtools/errorinfo.py
workflowwebtools/errorutils.py
workflowwebtools/globalerrors.py
workflowwebtools/listpage.py
workflowwebtools/manageactions.py
workflowwebtools/manageusers.py
workflowwebtools/paramsregression.py
workflowwebtools/procedures.py
workflowwebtools/reasonsmanip.py
workflowwebtools/serverconfig.py
workflowwebtools/statuses.py
workflowwebtools/workflowinfo.py
workflowwebtools/workflowtools.py
workflowwebtools.egg-info/PKG-INFO
workflowwebtools.egg-info/SOURCES.txt
workflowwebtools.egg-info/dependency_links.txt
workflowwebtools.egg-info/requires.txt
workflowwebtools.egg-info/top_level.txt
workflowwebtools/default/config.yml
workflowwebtools/predict/__init__.py
workflowwebtools/predict/evaluate.py
workflowwebtools/web/__init__.py
workflowwebtools/web/templates.py
workflowwebtools/web/static/css/globalerror.css
workflowwebtools/web/static/css/rotation.css
workflowwebtools/web/static/css/showlog.css
workflowwebtools/web/static/css/style.css
workflowwebtools/web/static/css/workflow.css
workflowwebtools/web/static/img/loading.gif
workflowwebtools/web/static/js/addreason.js
workflowwebtools/web/static/js/checkuser.js
workflowwebtools/web/static/js/datatable.js
workflowwebtools/web/static/js/datatable.js~
workflowwebtools/web/static/js/expandtable.js
workflowwebtools/web/static/js/globalerror.js
workflowwebtools/web/static/js/makeparams.js
workflowwebtools/web/static/js/pako_inflate.min.js
workflowwebtools/web/static/js/piechart.js
workflowwebtools/web/static/js/submit.js
workflowwebtools/web/static/js/wfwebtool.js
workflowwebtools/web/static/js/workflowtables.js
workflowwebtools/web/static/reports/actions.html
workflowwebtools/web/static/reports/actions.html~
