Metadata-Version: 1.0
Name: workflowwebtools
Version: 0.19.1
Summary: Provides a server for Production and Reprocessing operations
Home-page: https://github.com/CMSCompOps/WorkflowWebTools
Author: Daniel Abercrombie
Author-email: dabercro@mit.edu
License: UNKNOWN
Platform: UNKNOWN
